tabnet/__init__.py
tabnet/custom_objects.py
tabnet/stacked_tabnet.py
tabnet/tabnet.py
tabnet-0.1.6.dist-info/LICENSE
tabnet-0.1.6.dist-info/METADATA
tabnet-0.1.6.dist-info/WHEEL
tabnet-0.1.6.dist-info/top_level.txt
tabnet-0.1.6.dist-info/RECORD
