Metadata-Version: 2.1
Name: tabnet
Version: 0.1.6
Summary: Tensorflow 2.0 implementation of TabNet of any configuration.
Home-page: https://github.com/titu1994/tf-TabNet
Author: Somshubra Majumdar
Author-email: titu1994@gmail.com
License: MIT
Download-URL: https://github.com/titu1994/tf-TabNet
Platform: UNKNOWN
Classifier: Programming Language :: Python :: 3
Classifier: Programming Language :: Python :: 3.5
Classifier: Programming Language :: Python :: 3.6
Classifier: Programming Language :: Python :: 3.7
Classifier: License :: OSI Approved :: MIT License
Classifier: Operating System :: OS Independent
Classifier: Topic :: Software Development :: Libraries
Classifier: Topic :: Software Development :: Libraries :: Python Modules
Requires-Python: >=3.0.0
Provides-Extra: cpu
Requires-Dist: tensorflow ; extra == 'cpu'
Provides-Extra: gpu
Requires-Dist: tensorflow-gpu ; extra == 'gpu'
